flattener/entry_point.py
flattener/_version.py
flattener/__init__.py
flattener/__main__.py
Flattener-0.1.2.dist-info/DESCRIPTION.rst
Flattener-0.1.2.dist-info/METADATA
Flattener-0.1.2.dist-info/metadata.json
Flattener-0.1.2.dist-info/RECORD
Flattener-0.1.2.dist-info/top_level.txt
Flattener-0.1.2.dist-info/WHEEL
