Metadata-Version: 2.0
Name: Flattener
Version: 0.1.2
Summary: Flatten lists of lists.
Home-page: https://github.com/martinpengellyphillips/flattener
Author: Martin Pengelly-Phillips
Author-email: martin@4degrees.ltd.uk
License: Apache License (2.0)
Keywords: array,list,flatten
Platform: UNKNOWN
